Metadata-Version: 2.4
Name: quantaxis_run-lance
Version: 1.9
Summary: QUANTAXIS:Quantitative Financial Strategy Framework
Home-page: https://github.com/yutiansut/quantaxis_run
Author: yutiansut
Author-email: yutiansut@qq.com
License: MIT
Keywords: quantaxis,quant,finance,Backtest,Framework
Classifier: License :: OSI Approved :: MIT License
Classifier: Programming Language :: Python
Classifier: Intended Audience :: Developers
Classifier: Operating System :: OS Independent
Requires-Dist: celery>4
Requires-Dist: quantaxis-lance
Requires-Dist: qaenv
Dynamic: author
Dynamic: author-email
Dynamic: classifier
Dynamic: description
Dynamic: home-page
Dynamic: keywords
Dynamic: license
Dynamic: requires-dist
Dynamic: summary
